permon/VERSION
permon/__init__.py
permon/config.py
permon/exceptions.py
permon/security.py
permon/backend/__init__.py
permon/backend/stats/core.py
permon/backend/stats/jupyter.py
permon/frontend/__init__.py
permon/frontend/terminal.py
permon/frontend/utils.py
permon/frontend/assets/Raleway-Light.ttf
permon/frontend/assets/Raleway-Regular.ttf
permon/frontend/assets/RobotoMono-Regular.ttf
permon/frontend/assets/settings.svg
permon/frontend/assets/icon/android-chrome-192x192.png
permon/frontend/assets/icon/android-chrome-256x256.png
permon/frontend/assets/icon/apple-touch-icon.png
permon/frontend/assets/icon/browserconfig.xml
permon/frontend/assets/icon/favicon-16x16.png
permon/frontend/assets/icon/favicon-32x32.png
permon/frontend/assets/icon/favicon.ico
permon/frontend/assets/icon/icon.png
permon/frontend/assets/icon/mstile-150x150.png
permon/frontend/assets/icon/safari-pinned-tab.svg
permon/frontend/assets/icon/site.webmanifest
permon/frontend/browser/__init__.py
permon/frontend/browser/utils.py
permon/frontend/browser/dist/app.min.js
permon/frontend/browser/dist/login.min.js
permon/frontend/browser/dist/style.min.css
permon/frontend/browser/static/login.html
permon/frontend/browser/templates/index.html
permon/frontend/native/__init__.py
permon/frontend/native/utils.py
permon/frontend/native/qml/SettingsDrawer.qml
permon/frontend/native/qml/SettingsDrawer.qmlc
permon/frontend/native/qml/StatPage.qml
permon/frontend/native/qml/StatPage.qmlc
permon/frontend/native/qml/view.qml
permon/frontend/native/qml/view.qmlc
permon-2.0.1.dist-info/METADATA
permon-2.0.1.dist-info/RECORD
permon-2.0.1.dist-info/WHEEL
permon-2.0.1.dist-info/entry_points.txt
permon-2.0.1.dist-info/top_level.txt
