Metadata-Version: 2.1
Name: permon
Version: 2.0.1
Summary: A tool to monitor everything you want. Clean, simple, extensible and in one place.
Home-page: https://github.com/bminixhofer/permon
Author: Benjamin Minixhofer
Author-email: bminixhofer@gmail.com
License: MIT
Platform: UNKNOWN
Classifier: License :: OSI Approved :: MIT License
Classifier: Programming Language :: Python
Classifier: Programming Language :: Python :: 3
Classifier: Programming Language :: Python :: 3.6
Classifier: Programming Language :: Python :: Implementation :: CPython
Classifier: Programming Language :: Python :: Implementation :: PyPy
Requires-Python: >=3.6.0
Requires-Dist: psutil
Requires-Dist: appdirs
Requires-Dist: jupyter
Requires-Dist: pympler
